LICENSE.txt
MANIFEST.in
README.rst
setup.cfg
setup.py
amaretto/__init__.py
amaretto/amarettocore.py
amaretto/amarettorestore.py
amaretto/amarettostorage.py
amaretto.egg-info/PKG-INFO
amaretto.egg-info/SOURCES.txt
amaretto.egg-info/dependency_links.txt
amaretto.egg-info/top_level.txt
amaretto.egg-info/zip-safe