Metadata-Version: 1.1
Name: amaretto
Version: 0.0.2.10
Summary: Azure management tools by the1bit.
Home-page: https://github.com/the1bit/amaretto/tree/master/amaretto
Author: Tibor Kiss
Author-email: the1bithu@gmail.com
License: MIT
Keywords: azure management python microsoft the1bithu
Platform: UNKNOWN
Classifier: Development Status :: 3 - Alpha
Classifier: Intended Audience :: Developers
Classifier: Topic :: Software Development :: Build Tools
Classifier: Operating System :: POSIX :: Linux
Classifier: License :: OSI Approved :: MIT License
Classifier: Programming Language :: Python
Classifier: Programming Language :: Python :: 2
Classifier: Programming Language :: Python :: 2.7
Classifier: Programming Language :: Python :: 3
Classifier: Programming Language :: Python :: 3.4
Classifier: Programming Language :: Python :: 3.5
Classifier: Programming Language :: Python :: 3.6
